movsvalidator/__init__.py
movsvalidator/movsvalidator.py
movsvalidator/py.typed
zeed_movs_validator-0.0.3.dist-info/METADATA
zeed_movs_validator-0.0.3.dist-info/WHEEL
zeed_movs_validator-0.0.3.dist-info/entry_points.txt
zeed_movs_validator-0.0.3.dist-info/RECORD
