Metadata-Version: 2.1
Name: zeed-movs-validator
Version: 0.0.3
Classifier: Programming Language :: Python :: 3 :: Only
Classifier: Programming Language :: Python :: 3.12
Classifier: Programming Language :: Python :: 3.13
Project-URL: Homepage, https://github.com/ZeeD/movs-validator
Project-URL: Repository, https://github.com/ZeeD/movs-validator.git
Requires-Python: <3.14,>=3.12
Requires-Dist: zeed-movslib>=0.0.3
